micropayment_core/__init__.py
micropayment_core/keys.py
micropayment_core/scripts.py
micropayment_core/util.py
micropayment_core/version.py
micropayment_core-1.0.1.dist-info/DESCRIPTION.rst
micropayment_core-1.0.1.dist-info/METADATA
micropayment_core-1.0.1.dist-info/RECORD
micropayment_core-1.0.1.dist-info/WHEEL
micropayment_core-1.0.1.dist-info/metadata.json
micropayment_core-1.0.1.dist-info/top_level.txt
tests/__init__.py
tests/keys.py
tests/scripts.py
tests/util.py
