Metadata-Version: 2.0
Name: micropayment-core
Version: 1.0.1
Summary: Micropayment core utils for counterparty assets.
Home-page: http://storj.io
Author: Fabian Barkhau
Author-email: f483@storj.io
License: MIT
Keywords: storj,counterparty,micropayment,core
Platform: UNKNOWN
Classifier: Development Status :: 2 - Pre-Alpha
Classifier: Intended Audience :: Developers
Classifier: License :: OSI Approved :: MIT License
Classifier: Operating System :: OS Independent
Classifier: Programming Language :: Python
Classifier: Programming Language :: Python :: 2
Classifier: Programming Language :: Python :: 2.7
Classifier: Programming Language :: Python :: 3
Classifier: Programming Language :: Python :: 3.3
Classifier: Programming Language :: Python :: 3.4
Classifier: Topic :: Software Development :: Libraries :: Python Modules
Requires-Dist: ecdsa (>=0.13)
Requires-Dist: pycoin (==0.76)
